ibauth/__init__.py
ibauth/auth.py
ibauth/const.py
ibauth/logger.py
ibauth/models.py
ibauth/timing.py
ibauth/util.py
ibauth-0.1.4.dist-info/licenses/LICENSE.md
ibauth-0.1.4.dist-info/METADATA
ibauth-0.1.4.dist-info/WHEEL
ibauth-0.1.4.dist-info/entry_points.txt
ibauth-0.1.4.dist-info/top_level.txt
ibauth-0.1.4.dist-info/RECORD
