Metadata-Version: 2.4
Name: ibauth
Version: 0.1.4
Summary: Interactive Brokers OAuth
Author: Andrew Collier
Maintainer: Andrew Collier
Requires-Python: >=3.11
License-File: LICENSE.md
Requires-Dist: cryptography>=44.0.2
Requires-Dist: httpx>=0.28.1
Requires-Dist: pydantic>=2.11.10
Requires-Dist: pydantic-extra-types>=2.11.0
Requires-Dist: pyjwt>=2.10.1
Requires-Dist: pyyaml>=6.0.2
Requires-Dist: tenacity>=9.0.0
Dynamic: license-file
